[
    {
        "kind": "struct/member",
        "name": "fuchsia.ui.gfx/AddChildCmd.child_id",
        "type": "uint32"
    },
    {
        "kind": "struct/member",
        "name": "fuchsia.ui.gfx/AddChildCmd.node_id",
        "type": "uint32"
    },
    {
        "kind": "struct",
        "name": "fuchsia.ui.gfx/AddChildCmd"
    },
    {
        "kind": "struct/member",
        "name": "fuchsia.ui.gfx/AddLayerCmd.layer_id",
        "type": "uint32"
    },
    {
        "kind": "struct/member",
        "name": "fuchsia.ui.gfx/AddLayerCmd.layer_stack_id",
        "type": "uint32"
    },
    {
        "kind": "struct",
        "name": "fuchsia.ui.gfx/AddLayerCmd"
    },
    {
        "kind": "struct/member",
        "name": "fuchsia.ui.gfx/AddLightCmd.light_id",
        "type": "uint32"
    },
    {
        "kind": "struct/member",
        "name": "fuchsia.ui.gfx/AddLightCmd.scene_id",
        "type": "uint32"
    },
    {
        "kind": "struct",
        "name": "fuchsia.ui.gfx/AddLightCmd"
    },
    {
        "kind": "struct/member",
        "name": "fuchsia.ui.gfx/AddPartCmd.node_id",
        "type": "uint32"
    },
    {
        "kind": "struct/member",
        "name": "fuchsia.ui.gfx/AddPartCmd.part_id",
        "type": "uint32"
    },
    {
        "kind": "struct",
        "name": "fuchsia.ui.gfx/AddPartCmd"
    },
    {
        "kind": "struct/member",
        "name": "fuchsia.ui.gfx/AmbientLightArgs.dummy",
        "type": "uint32",
        "value": "0"
    },
    {
        "kind": "struct",
        "name": "fuchsia.ui.gfx/AmbientLightArgs"
    },
    {
        "kind": "struct/member",
        "name": "fuchsia.ui.gfx/BindMeshBuffersCmd.bounding_box",
        "type": "fuchsia.ui.gfx/BoundingBox"
    },
    {
        "kind": "struct/member",
        "name": "fuchsia.ui.gfx/BindMeshBuffersCmd.index_buffer_id",
        "type": "uint32"
    },
    {
        "kind": "struct/member",
        "name": "fuchsia.ui.gfx/BindMeshBuffersCmd.index_count",
        "type": "uint32"
    },
    {
        "kind": "struct/member",
        "name": "fuchsia.ui.gfx/BindMeshBuffersCmd.index_format",
        "type": "fuchsia.ui.gfx/MeshIndexFormat"
    },
    {
        "kind": "struct/member",
        "name": "fuchsia.ui.gfx/BindMeshBuffersCmd.index_offset",
        "type": "uint64"
    },
    {
        "kind": "struct/member",
        "name": "fuchsia.ui.gfx/BindMeshBuffersCmd.mesh_id",
        "type": "uint32"
    },
    {
        "kind": "struct/member",
        "name": "fuchsia.ui.gfx/BindMeshBuffersCmd.vertex_buffer_id",
        "type": "uint32"
    },
    {
        "kind": "struct/member",
        "name": "fuchsia.ui.gfx/BindMeshBuffersCmd.vertex_count",
        "type": "uint32"
    },
    {
        "kind": "struct/member",
        "name": "fuchsia.ui.gfx/BindMeshBuffersCmd.vertex_format",
        "type": "fuchsia.ui.gfx/MeshVertexFormat"
    },
    {
        "kind": "struct/member",
        "name": "fuchsia.ui.gfx/BindMeshBuffersCmd.vertex_offset",
        "type": "uint64"
    },
    {
        "kind": "struct",
        "name": "fuchsia.ui.gfx/BindMeshBuffersCmd"
    },
    {
        "kind": "struct/member",
        "name": "fuchsia.ui.gfx/BoundingBox.max",
        "type": "fuchsia.ui.gfx/vec3"
    },
    {
        "kind": "struct/member",
        "name": "fuchsia.ui.gfx/BoundingBox.min",
        "type": "fuchsia.ui.gfx/vec3"
    },
    {
        "kind": "struct",
        "name": "fuchsia.ui.gfx/BoundingBox"
    },
    {
        "kind": "struct/member",
        "name": "fuchsia.ui.gfx/BufferArgs.memory_id",
        "type": "uint32"
    },
    {
        "kind": "struct/member",
        "name": "fuchsia.ui.gfx/BufferArgs.memory_offset",
        "type": "uint32"
    },
    {
        "kind": "struct/member",
        "name": "fuchsia.ui.gfx/BufferArgs.num_bytes",
        "type": "uint32"
    },
    {
        "kind": "struct",
        "name": "fuchsia.ui.gfx/BufferArgs"
    },
    {
        "kind": "struct/member",
        "name": "fuchsia.ui.gfx/CameraArgs.scene_id",
        "type": "uint32"
    },
    {
        "kind": "struct",
        "name": "fuchsia.ui.gfx/CameraArgs"
    },
    {
        "kind": "struct/member",
        "name": "fuchsia.ui.gfx/CircleArgs.radius",
        "type": "fuchsia.ui.gfx/Value"
    },
    {
        "kind": "struct",
        "name": "fuchsia.ui.gfx/CircleArgs"
    },
    {
        "kind": "struct/member",
        "name": "fuchsia.ui.gfx/ClipNodeArgs.unused",
        "type": "uint32",
        "value": "0"
    },
    {
        "kind": "struct",
        "name": "fuchsia.ui.gfx/ClipNodeArgs"
    },
    {
        "kind": "struct/member",
        "name": "fuchsia.ui.gfx/ColorRgb.blue",
        "type": "float32"
    },
    {
        "kind": "struct/member",
        "name": "fuchsia.ui.gfx/ColorRgb.green",
        "type": "float32"
    },
    {
        "kind": "struct/member",
        "name": "fuchsia.ui.gfx/ColorRgb.red",
        "type": "float32"
    },
    {
        "kind": "struct",
        "name": "fuchsia.ui.gfx/ColorRgb"
    },
    {
        "kind": "struct/member",
        "name": "fuchsia.ui.gfx/ColorRgbValue.value",
        "type": "fuchsia.ui.gfx/ColorRgb"
    },
    {
        "kind": "struct/member",
        "name": "fuchsia.ui.gfx/ColorRgbValue.variable_id",
        "type": "uint32"
    },
    {
        "kind": "struct",
        "name": "fuchsia.ui.gfx/ColorRgbValue"
    },
    {
        "kind": "struct/member",
        "name": "fuchsia.ui.gfx/ColorRgba.alpha",
        "type": "uint8"
    },
    {
        "kind": "struct/member",
        "name": "fuchsia.ui.gfx/ColorRgba.blue",
        "type": "uint8"
    },
    {
        "kind": "struct/member",
        "name": "fuchsia.ui.gfx/ColorRgba.green",
        "type": "uint8"
    },
    {
        "kind": "struct/member",
        "name": "fuchsia.ui.gfx/ColorRgba.red",
        "type": "uint8"
    },
    {
        "kind": "struct",
        "name": "fuchsia.ui.gfx/ColorRgba"
    },
    {
        "kind": "struct/member",
        "name": "fuchsia.ui.gfx/ColorRgbaValue.value",
        "type": "fuchsia.ui.gfx/ColorRgba"
    },
    {
        "kind": "struct/member",
        "name": "fuchsia.ui.gfx/ColorRgbaValue.variable_id",
        "type": "uint32"
    },
    {
        "kind": "struct",
        "name": "fuchsia.ui.gfx/ColorRgbaValue"
    },
    {
        "kind": "union/member",
        "name": "fuchsia.ui.gfx/Command.add_child",
        "type": "fuchsia.ui.gfx/AddChildCmd"
    },
    {
        "kind": "union/member",
        "name": "fuchsia.ui.gfx/Command.add_layer",
        "type": "fuchsia.ui.gfx/AddLayerCmd"
    },
    {
        "kind": "union/member",
        "name": "fuchsia.ui.gfx/Command.add_light",
        "type": "fuchsia.ui.gfx/AddLightCmd"
    },
    {
        "kind": "union/member",
        "name": "fuchsia.ui.gfx/Command.add_part",
        "type": "fuchsia.ui.gfx/AddPartCmd"
    },
    {
        "kind": "union/member",
        "name": "fuchsia.ui.gfx/Command.bind_mesh_buffers",
        "type": "fuchsia.ui.gfx/BindMeshBuffersCmd"
    },
    {
        "kind": "union/member",
        "name": "fuchsia.ui.gfx/Command.create_resource",
        "type": "fuchsia.ui.gfx/CreateResourceCmd"
    },
    {
        "kind": "union/member",
        "name": "fuchsia.ui.gfx/Command.detach",
        "type": "fuchsia.ui.gfx/DetachCmd"
    },
    {
        "kind": "union/member",
        "name": "fuchsia.ui.gfx/Command.detach_children",
        "type": "fuchsia.ui.gfx/DetachChildrenCmd"
    },
    {
        "kind": "union/member",
        "name": "fuchsia.ui.gfx/Command.detach_light",
        "type": "fuchsia.ui.gfx/DetachLightCmd"
    },
    {
        "kind": "union/member",
        "name": "fuchsia.ui.gfx/Command.detach_lights",
        "type": "fuchsia.ui.gfx/DetachLightsCmd"
    },
    {
        "kind": "union/member",
        "name": "fuchsia.ui.gfx/Command.export_resource",
        "type": "fuchsia.ui.gfx/ExportResourceCmdDeprecated"
    },
    {
        "kind": "union/member",
        "name": "fuchsia.ui.gfx/Command.import_resource",
        "type": "fuchsia.ui.gfx/ImportResourceCmdDeprecated"
    },
    {
        "kind": "union/member",
        "name": "fuchsia.ui.gfx/Command.release_resource",
        "type": "fuchsia.ui.gfx/ReleaseResourceCmd"
    },
    {
        "kind": "union/member",
        "name": "fuchsia.ui.gfx/Command.remove_all_layers",
        "type": "fuchsia.ui.gfx/RemoveAllLayersCmd"
    },
    {
        "kind": "union/member",
        "name": "fuchsia.ui.gfx/Command.remove_layer",
        "type": "fuchsia.ui.gfx/RemoveLayerCmd"
    },
    {
        "kind": "union/member",
        "name": "fuchsia.ui.gfx/Command.scene__add_ambient_light",
        "type": "fuchsia.ui.gfx/SceneAddAmbientLightCmd"
    },
    {
        "kind": "union/member",
        "name": "fuchsia.ui.gfx/Command.scene__add_directional_light",
        "type": "fuchsia.ui.gfx/SceneAddDirectionalLightCmd"
    },
    {
        "kind": "union/member",
        "name": "fuchsia.ui.gfx/Command.scene__add_point_light",
        "type": "fuchsia.ui.gfx/SceneAddPointLightCmd"
    },
    {
        "kind": "union/member",
        "name": "fuchsia.ui.gfx/Command.send_size_change_hint_hack",
        "type": "fuchsia.ui.gfx/SendSizeChangeHintCmdHACK"
    },
    {
        "kind": "union/member",
        "name": "fuchsia.ui.gfx/Command.set_anchor",
        "type": "fuchsia.ui.gfx/SetAnchorCmd"
    },
    {
        "kind": "union/member",
        "name": "fuchsia.ui.gfx/Command.set_camera",
        "type": "fuchsia.ui.gfx/SetCameraCmd"
    },
    {
        "kind": "union/member",
        "name": "fuchsia.ui.gfx/Command.set_camera_clip_space_transform",
        "type": "fuchsia.ui.gfx/SetCameraClipSpaceTransformCmd"
    },
    {
        "kind": "union/member",
        "name": "fuchsia.ui.gfx/Command.set_camera_pose_buffer",
        "type": "fuchsia.ui.gfx/SetCameraPoseBufferCmd"
    },
    {
        "kind": "union/member",
        "name": "fuchsia.ui.gfx/Command.set_camera_projection",
        "type": "fuchsia.ui.gfx/SetCameraProjectionCmd"
    },
    {
        "kind": "union/member",
        "name": "fuchsia.ui.gfx/Command.set_camera_transform",
        "type": "fuchsia.ui.gfx/SetCameraTransformCmd"
    },
    {
        "kind": "union/member",
        "name": "fuchsia.ui.gfx/Command.set_clip",
        "type": "fuchsia.ui.gfx/SetClipCmd"
    },
    {
        "kind": "union/member",
        "name": "fuchsia.ui.gfx/Command.set_clip_planes",
        "type": "fuchsia.ui.gfx/SetClipPlanesCmd"
    },
    {
        "kind": "union/member",
        "name": "fuchsia.ui.gfx/Command.set_color",
        "type": "fuchsia.ui.gfx/SetColorCmd"
    },
    {
        "kind": "union/member",
        "name": "fuchsia.ui.gfx/Command.set_disable_clipping",
        "type": "fuchsia.ui.gfx/SetDisableClippingCmd"
    },
    {
        "kind": "union/member",
        "name": "fuchsia.ui.gfx/Command.set_display_color_conversion",
        "type": "fuchsia.ui.gfx/SetDisplayColorConversionCmdHACK"
    },
    {
        "kind": "union/member",
        "name": "fuchsia.ui.gfx/Command.set_display_minimum_rgb",
        "type": "fuchsia.ui.gfx/SetDisplayMinimumRgbCmdHACK"
    },
    {
        "kind": "union/member",
        "name": "fuchsia.ui.gfx/Command.set_display_rotation",
        "type": "fuchsia.ui.gfx/SetDisplayRotationCmdHACK"
    },
    {
        "kind": "union/member",
        "name": "fuchsia.ui.gfx/Command.set_enable_view_debug_bounds",
        "type": "fuchsia.ui.gfx/SetEnableDebugViewBoundsCmd"
    },
    {
        "kind": "union/member",
        "name": "fuchsia.ui.gfx/Command.set_event_mask",
        "type": "fuchsia.ui.gfx/SetEventMaskCmd"
    },
    {
        "kind": "union/member",
        "name": "fuchsia.ui.gfx/Command.set_hit_test_behavior",
        "type": "fuchsia.ui.gfx/SetHitTestBehaviorCmd"
    },
    {
        "kind": "union/member",
        "name": "fuchsia.ui.gfx/Command.set_import_focus",
        "type": "fuchsia.ui.gfx/SetImportFocusCmdDEPRECATED"
    },
    {
        "kind": "union/member",
        "name": "fuchsia.ui.gfx/Command.set_label",
        "type": "fuchsia.ui.gfx/SetLabelCmd"
    },
    {
        "kind": "union/member",
        "name": "fuchsia.ui.gfx/Command.set_layer_stack",
        "type": "fuchsia.ui.gfx/SetLayerStackCmd"
    },
    {
        "kind": "union/member",
        "name": "fuchsia.ui.gfx/Command.set_light_color",
        "type": "fuchsia.ui.gfx/SetLightColorCmd"
    },
    {
        "kind": "union/member",
        "name": "fuchsia.ui.gfx/Command.set_light_direction",
        "type": "fuchsia.ui.gfx/SetLightDirectionCmd"
    },
    {
        "kind": "union/member",
        "name": "fuchsia.ui.gfx/Command.set_material",
        "type": "fuchsia.ui.gfx/SetMaterialCmd"
    },
    {
        "kind": "union/member",
        "name": "fuchsia.ui.gfx/Command.set_opacity",
        "type": "fuchsia.ui.gfx/SetOpacityCmd"
    },
    {
        "kind": "union/member",
        "name": "fuchsia.ui.gfx/Command.set_point_light_falloff",
        "type": "fuchsia.ui.gfx/SetPointLightFalloffCmd"
    },
    {
        "kind": "union/member",
        "name": "fuchsia.ui.gfx/Command.set_point_light_position",
        "type": "fuchsia.ui.gfx/SetPointLightPositionCmd"
    },
    {
        "kind": "union/member",
        "name": "fuchsia.ui.gfx/Command.set_renderer",
        "type": "fuchsia.ui.gfx/SetRendererCmd"
    },
    {
        "kind": "union/member",
        "name": "fuchsia.ui.gfx/Command.set_renderer_param",
        "type": "fuchsia.ui.gfx/SetRendererParamCmd"
    },
    {
        "kind": "union/member",
        "name": "fuchsia.ui.gfx/Command.set_rotation",
        "type": "fuchsia.ui.gfx/SetRotationCmd"
    },
    {
        "kind": "union/member",
        "name": "fuchsia.ui.gfx/Command.set_scale",
        "type": "fuchsia.ui.gfx/SetScaleCmd"
    },
    {
        "kind": "union/member",
        "name": "fuchsia.ui.gfx/Command.set_semantic_visibility",
        "type": "fuchsia.ui.gfx/SetSemanticVisibilityCmd"
    },
    {
        "kind": "union/member",
        "name": "fuchsia.ui.gfx/Command.set_shape",
        "type": "fuchsia.ui.gfx/SetShapeCmd"
    },
    {
        "kind": "union/member",
        "name": "fuchsia.ui.gfx/Command.set_size",
        "type": "fuchsia.ui.gfx/SetSizeCmd"
    },
    {
        "kind": "union/member",
        "name": "fuchsia.ui.gfx/Command.set_stereo_camera_projection",
        "type": "fuchsia.ui.gfx/SetStereoCameraProjectionCmd"
    },
    {
        "kind": "union/member",
        "name": "fuchsia.ui.gfx/Command.set_tag",
        "type": "fuchsia.ui.gfx/SetTagCmd"
    },
    {
        "kind": "union/member",
        "name": "fuchsia.ui.gfx/Command.set_texture",
        "type": "fuchsia.ui.gfx/SetTextureCmd"
    },
    {
        "kind": "union/member",
        "name": "fuchsia.ui.gfx/Command.set_translation",
        "type": "fuchsia.ui.gfx/SetTranslationCmd"
    },
    {
        "kind": "union/member",
        "name": "fuchsia.ui.gfx/Command.set_view_holder_bounds_color",
        "type": "fuchsia.ui.gfx/SetViewHolderBoundsColorCmd"
    },
    {
        "kind": "union/member",
        "name": "fuchsia.ui.gfx/Command.set_view_properties",
        "type": "fuchsia.ui.gfx/SetViewPropertiesCmd"
    },
    {
        "kind": "union/member",
        "name": "fuchsia.ui.gfx/Command.take_snapshot_cmd",
        "type": "fuchsia.ui.gfx/TakeSnapshotCmdDEPRECATED"
    },
    {
        "kind": "union",
        "name": "fuchsia.ui.gfx/Command",
        "resourceness": "resource",
        "strictness": "strict"
    },
    {
        "kind": "struct/member",
        "name": "fuchsia.ui.gfx/CompositorArgs.dummy",
        "type": "uint32",
        "value": "0"
    },
    {
        "kind": "struct",
        "name": "fuchsia.ui.gfx/CompositorArgs"
    },
    {
        "kind": "struct/member",
        "name": "fuchsia.ui.gfx/CreateResourceCmd.id",
        "type": "uint32"
    },
    {
        "kind": "struct/member",
        "name": "fuchsia.ui.gfx/CreateResourceCmd.resource",
        "type": "fuchsia.ui.gfx/ResourceArgs"
    },
    {
        "kind": "struct",
        "name": "fuchsia.ui.gfx/CreateResourceCmd",
        "resourceness": "resource"
    },
    {
        "kind": "struct/member",
        "name": "fuchsia.ui.gfx/DetachChildrenCmd.node_id",
        "type": "uint32"
    },
    {
        "kind": "struct",
        "name": "fuchsia.ui.gfx/DetachChildrenCmd"
    },
    {
        "kind": "struct/member",
        "name": "fuchsia.ui.gfx/DetachCmd.id",
        "type": "uint32"
    },
    {
        "kind": "struct",
        "name": "fuchsia.ui.gfx/DetachCmd"
    },
    {
        "kind": "struct/member",
        "name": "fuchsia.ui.gfx/DetachLightCmd.light_id",
        "type": "uint32"
    },
    {
        "kind": "struct",
        "name": "fuchsia.ui.gfx/DetachLightCmd"
    },
    {
        "kind": "struct/member",
        "name": "fuchsia.ui.gfx/DetachLightsCmd.scene_id",
        "type": "uint32"
    },
    {
        "kind": "struct",
        "name": "fuchsia.ui.gfx/DetachLightsCmd"
    },
    {
        "kind": "struct/member",
        "name": "fuchsia.ui.gfx/DirectionalLightArgs.dummy",
        "type": "uint32",
        "value": "0"
    },
    {
        "kind": "struct",
        "name": "fuchsia.ui.gfx/DirectionalLightArgs"
    },
    {
        "kind": "struct/member",
        "name": "fuchsia.ui.gfx/DisplayCompositorArgs.dummy",
        "type": "uint32",
        "value": "0"
    },
    {
        "kind": "struct",
        "name": "fuchsia.ui.gfx/DisplayCompositorArgs"
    },
    {
        "kind": "struct/member",
        "name": "fuchsia.ui.gfx/DisplayInfo.height_in_px",
        "type": "uint32"
    },
    {
        "kind": "struct/member",
        "name": "fuchsia.ui.gfx/DisplayInfo.width_in_px",
        "type": "uint32"
    },
    {
        "kind": "struct",
        "name": "fuchsia.ui.gfx/DisplayInfo"
    },
    {
        "kind": "struct/member",
        "name": "fuchsia.ui.gfx/EntityNodeArgs.unused",
        "type": "uint32",
        "value": "0"
    },
    {
        "kind": "struct",
        "name": "fuchsia.ui.gfx/EntityNodeArgs"
    },
    {
        "kind": "union/member",
        "name": "fuchsia.ui.gfx/Event.import_unbound",
        "type": "fuchsia.ui.gfx/ImportUnboundEvent"
    },
    {
        "kind": "union/member",
        "name": "fuchsia.ui.gfx/Event.metrics",
        "type": "fuchsia.ui.gfx/MetricsEvent"
    },
    {
        "kind": "union/member",
        "name": "fuchsia.ui.gfx/Event.size_change_hint",
        "type": "fuchsia.ui.gfx/SizeChangeHintEvent"
    },
    {
        "kind": "union/member",
        "name": "fuchsia.ui.gfx/Event.view_attached_to_scene",
        "type": "fuchsia.ui.gfx/ViewAttachedToSceneEvent"
    },
    {
        "kind": "union/member",
        "name": "fuchsia.ui.gfx/Event.view_connected",
        "type": "fuchsia.ui.gfx/ViewConnectedEvent"
    },
    {
        "kind": "union/member",
        "name": "fuchsia.ui.gfx/Event.view_detached_from_scene",
        "type": "fuchsia.ui.gfx/ViewDetachedFromSceneEvent"
    },
    {
        "kind": "union/member",
        "name": "fuchsia.ui.gfx/Event.view_disconnected",
        "type": "fuchsia.ui.gfx/ViewDisconnectedEvent"
    },
    {
        "kind": "union/member",
        "name": "fuchsia.ui.gfx/Event.view_holder_connected",
        "type": "fuchsia.ui.gfx/ViewHolderConnectedEvent"
    },
    {
        "kind": "union/member",
        "name": "fuchsia.ui.gfx/Event.view_holder_disconnected",
        "type": "fuchsia.ui.gfx/ViewHolderDisconnectedEvent"
    },
    {
        "kind": "union/member",
        "name": "fuchsia.ui.gfx/Event.view_properties_changed",
        "type": "fuchsia.ui.gfx/ViewPropertiesChangedEvent"
    },
    {
        "kind": "union/member",
        "name": "fuchsia.ui.gfx/Event.view_state_changed",
        "type": "fuchsia.ui.gfx/ViewStateChangedEvent"
    },
    {
        "kind": "union",
        "name": "fuchsia.ui.gfx/Event",
        "strictness": "strict"
    },
    {
        "kind": "struct/member",
        "name": "fuchsia.ui.gfx/ExportResourceCmdDeprecated.id",
        "type": "uint32"
    },
    {
        "kind": "struct/member",
        "name": "fuchsia.ui.gfx/ExportResourceCmdDeprecated.token",
        "type": "zx/handle:EVENTPAIR"
    },
    {
        "kind": "struct",
        "name": "fuchsia.ui.gfx/ExportResourceCmdDeprecated",
        "resourceness": "resource"
    },
    {
        "kind": "struct/member",
        "name": "fuchsia.ui.gfx/ExportToken.value",
        "type": "zx/handle:EVENTPAIR"
    },
    {
        "kind": "struct",
        "name": "fuchsia.ui.gfx/ExportToken",
        "resourceness": "resource"
    },
    {
        "kind": "struct/member",
        "name": "fuchsia.ui.gfx/FactoredTransform.anchor",
        "type": "fuchsia.ui.gfx/vec3"
    },
    {
        "kind": "struct/member",
        "name": "fuchsia.ui.gfx/FactoredTransform.rotation",
        "type": "fuchsia.ui.gfx/Quaternion"
    },
    {
        "kind": "struct/member",
        "name": "fuchsia.ui.gfx/FactoredTransform.scale",
        "type": "fuchsia.ui.gfx/vec3"
    },
    {
        "kind": "struct/member",
        "name": "fuchsia.ui.gfx/FactoredTransform.translation",
        "type": "fuchsia.ui.gfx/vec3"
    },
    {
        "kind": "struct",
        "name": "fuchsia.ui.gfx/FactoredTransform"
    },
    {
        "kind": "struct/member",
        "name": "fuchsia.ui.gfx/FloatValue.value",
        "type": "float32"
    },
    {
        "kind": "struct/member",
        "name": "fuchsia.ui.gfx/FloatValue.variable_id",
        "type": "uint32"
    },
    {
        "kind": "struct",
        "name": "fuchsia.ui.gfx/FloatValue"
    },
    {
        "kind": "enum/member",
        "name": "fuchsia.ui.gfx/HitTestBehavior.kDefault",
        "value": "0"
    },
    {
        "kind": "enum/member",
        "name": "fuchsia.ui.gfx/HitTestBehavior.kSuppress",
        "value": "1"
    },
    {
        "kind": "enum",
        "name": "fuchsia.ui.gfx/HitTestBehavior",
        "strictness": "strict",
        "type": "uint32"
    },
    {
        "kind": "struct/member",
        "name": "fuchsia.ui.gfx/ImageArgs.info",
        "type": "fuchsia.images/ImageInfo"
    },
    {
        "kind": "struct/member",
        "name": "fuchsia.ui.gfx/ImageArgs.memory_id",
        "type": "uint32"
    },
    {
        "kind": "struct/member",
        "name": "fuchsia.ui.gfx/ImageArgs.memory_offset",
        "type": "uint32"
    },
    {
        "kind": "struct",
        "name": "fuchsia.ui.gfx/ImageArgs"
    },
    {
        "kind": "struct/member",
        "name": "fuchsia.ui.gfx/ImageArgs2.buffer_collection_id",
        "type": "uint32"
    },
    {
        "kind": "struct/member",
        "name": "fuchsia.ui.gfx/ImageArgs2.buffer_collection_index",
        "type": "uint32"
    },
    {
        "kind": "struct/member",
        "name": "fuchsia.ui.gfx/ImageArgs2.height",
        "type": "uint32"
    },
    {
        "kind": "struct/member",
        "name": "fuchsia.ui.gfx/ImageArgs2.width",
        "type": "uint32"
    },
    {
        "kind": "struct",
        "name": "fuchsia.ui.gfx/ImageArgs2"
    },
    {
        "kind": "struct/member",
        "name": "fuchsia.ui.gfx/ImageArgs3.buffer_collection_index",
        "type": "uint32"
    },
    {
        "kind": "struct/member",
        "name": "fuchsia.ui.gfx/ImageArgs3.height",
        "type": "uint32"
    },
    {
        "kind": "struct/member",
        "name": "fuchsia.ui.gfx/ImageArgs3.import_token",
        "type": "fuchsia.ui.composition/BufferCollectionImportToken"
    },
    {
        "kind": "struct/member",
        "name": "fuchsia.ui.gfx/ImageArgs3.width",
        "type": "uint32"
    },
    {
        "kind": "struct",
        "name": "fuchsia.ui.gfx/ImageArgs3",
        "resourceness": "resource"
    },
    {
        "kind": "struct/member",
        "name": "fuchsia.ui.gfx/ImagePipe2Args.image_pipe_request",
        "type": "server_end:fuchsia.images/ImagePipe2"
    },
    {
        "kind": "struct",
        "name": "fuchsia.ui.gfx/ImagePipe2Args",
        "resourceness": "resource"
    },
    {
        "kind": "struct/member",
        "name": "fuchsia.ui.gfx/ImportResourceCmdDeprecated.id",
        "type": "uint32"
    },
    {
        "kind": "struct/member",
        "name": "fuchsia.ui.gfx/ImportResourceCmdDeprecated.spec",
        "type": "fuchsia.ui.gfx/ImportSpec"
    },
    {
        "kind": "struct/member",
        "name": "fuchsia.ui.gfx/ImportResourceCmdDeprecated.token",
        "type": "zx/handle:EVENTPAIR"
    },
    {
        "kind": "struct",
        "name": "fuchsia.ui.gfx/ImportResourceCmdDeprecated",
        "resourceness": "resource"
    },
    {
        "kind": "enum/member",
        "name": "fuchsia.ui.gfx/ImportSpec.NODE",
        "value": "0"
    },
    {
        "kind": "enum",
        "name": "fuchsia.ui.gfx/ImportSpec",
        "strictness": "strict",
        "type": "uint32"
    },
    {
        "kind": "struct/member",
        "name": "fuchsia.ui.gfx/ImportToken.value",
        "type": "zx/handle:EVENTPAIR"
    },
    {
        "kind": "struct",
        "name": "fuchsia.ui.gfx/ImportToken",
        "resourceness": "resource"
    },
    {
        "kind": "struct/member",
        "name": "fuchsia.ui.gfx/ImportUnboundEvent.resource_id",
        "type": "uint32"
    },
    {
        "kind": "struct",
        "name": "fuchsia.ui.gfx/ImportUnboundEvent"
    },
    {
        "kind": "struct/member",
        "name": "fuchsia.ui.gfx/LayerArgs.dummy",
        "type": "uint32",
        "value": "0"
    },
    {
        "kind": "struct",
        "name": "fuchsia.ui.gfx/LayerArgs"
    },
    {
        "kind": "struct/member",
        "name": "fuchsia.ui.gfx/LayerStackArgs.dummy",
        "type": "uint32",
        "value": "0"
    },
    {
        "kind": "struct",
        "name": "fuchsia.ui.gfx/LayerStackArgs"
    },
    {
        "kind": "struct/member",
        "name": "fuchsia.ui.gfx/MaterialArgs.dummy",
        "type": "uint32",
        "value": "0"
    },
    {
        "kind": "struct",
        "name": "fuchsia.ui.gfx/MaterialArgs"
    },
    {
        "kind": "struct/member",
        "name": "fuchsia.ui.gfx/Matrix4Value.value",
        "type": "fuchsia.ui.gfx/mat4"
    },
    {
        "kind": "struct/member",
        "name": "fuchsia.ui.gfx/Matrix4Value.variable_id",
        "type": "uint32"
    },
    {
        "kind": "struct",
        "name": "fuchsia.ui.gfx/Matrix4Value"
    },
    {
        "kind": "struct/member",
        "name": "fuchsia.ui.gfx/MemoryArgs.allocation_size",
        "type": "uint64"
    },
    {
        "kind": "struct/member",
        "name": "fuchsia.ui.gfx/MemoryArgs.memory_type",
        "type": "fuchsia.images/MemoryType"
    },
    {
        "kind": "struct/member",
        "name": "fuchsia.ui.gfx/MemoryArgs.vmo",
        "type": "zx/handle:VMO"
    },
    {
        "kind": "struct",
        "name": "fuchsia.ui.gfx/MemoryArgs",
        "resourceness": "resource"
    },
    {
        "kind": "struct",
        "name": "fuchsia.ui.gfx/MeshArgs"
    },
    {
        "kind": "enum/member",
        "name": "fuchsia.ui.gfx/MeshIndexFormat.kUint16",
        "value": "1"
    },
    {
        "kind": "enum/member",
        "name": "fuchsia.ui.gfx/MeshIndexFormat.kUint32",
        "value": "2"
    },
    {
        "kind": "enum",
        "name": "fuchsia.ui.gfx/MeshIndexFormat",
        "strictness": "strict",
        "type": "uint32"
    },
    {
        "kind": "struct/member",
        "name": "fuchsia.ui.gfx/MeshVertexFormat.normal_type",
        "type": "fuchsia.ui.gfx/ValueType"
    },
    {
        "kind": "struct/member",
        "name": "fuchsia.ui.gfx/MeshVertexFormat.position_type",
        "type": "fuchsia.ui.gfx/ValueType"
    },
    {
        "kind": "struct/member",
        "name": "fuchsia.ui.gfx/MeshVertexFormat.tex_coord_type",
        "type": "fuchsia.ui.gfx/ValueType"
    },
    {
        "kind": "struct",
        "name": "fuchsia.ui.gfx/MeshVertexFormat"
    },
    {
        "kind": "struct/member",
        "name": "fuchsia.ui.gfx/Metrics.scale_x",
        "type": "float32"
    },
    {
        "kind": "struct/member",
        "name": "fuchsia.ui.gfx/Metrics.scale_y",
        "type": "float32"
    },
    {
        "kind": "struct/member",
        "name": "fuchsia.ui.gfx/Metrics.scale_z",
        "type": "float32"
    },
    {
        "kind": "struct",
        "name": "fuchsia.ui.gfx/Metrics"
    },
    {
        "kind": "struct/member",
        "name": "fuchsia.ui.gfx/MetricsEvent.metrics",
        "type": "fuchsia.ui.gfx/Metrics"
    },
    {
        "kind": "struct/member",
        "name": "fuchsia.ui.gfx/MetricsEvent.node_id",
        "type": "uint32"
    },
    {
        "kind": "struct",
        "name": "fuchsia.ui.gfx/MetricsEvent"
    },
    {
        "kind": "struct/member",
        "name": "fuchsia.ui.gfx/OpacityNodeArgsHACK.unused",
        "type": "uint32",
        "value": "0"
    },
    {
        "kind": "struct",
        "name": "fuchsia.ui.gfx/OpacityNodeArgsHACK"
    },
    {
        "kind": "struct/member",
        "name": "fuchsia.ui.gfx/Plane3.dir",
        "type": "fuchsia.ui.gfx/vec3"
    },
    {
        "kind": "struct/member",
        "name": "fuchsia.ui.gfx/Plane3.dist",
        "type": "float32"
    },
    {
        "kind": "struct",
        "name": "fuchsia.ui.gfx/Plane3"
    },
    {
        "kind": "struct/member",
        "name": "fuchsia.ui.gfx/PointLightArgs.dummy",
        "type": "uint32",
        "value": "0"
    },
    {
        "kind": "struct",
        "name": "fuchsia.ui.gfx/PointLightArgs"
    },
    {
        "kind": "protocol/member",
        "name": "fuchsia.ui.gfx/PoseBufferProvider.SetPoseBuffer",
        "type": "(zx/handle:VMO buffer,uint32 num_entries,int64 base_time,uint64 time_interval)"
    },
    {
        "kind": "protocol",
        "name": "fuchsia.ui.gfx/PoseBufferProvider"
    },
    {
        "kind": "struct/member",
        "name": "fuchsia.ui.gfx/Quaternion.w",
        "type": "float32"
    },
    {
        "kind": "struct/member",
        "name": "fuchsia.ui.gfx/Quaternion.x",
        "type": "float32"
    },
    {
        "kind": "struct/member",
        "name": "fuchsia.ui.gfx/Quaternion.y",
        "type": "float32"
    },
    {
        "kind": "struct/member",
        "name": "fuchsia.ui.gfx/Quaternion.z",
        "type": "float32"
    },
    {
        "kind": "struct",
        "name": "fuchsia.ui.gfx/Quaternion"
    },
    {
        "kind": "struct/member",
        "name": "fuchsia.ui.gfx/QuaternionValue.value",
        "type": "fuchsia.ui.gfx/Quaternion"
    },
    {
        "kind": "struct/member",
        "name": "fuchsia.ui.gfx/QuaternionValue.variable_id",
        "type": "uint32"
    },
    {
        "kind": "struct",
        "name": "fuchsia.ui.gfx/QuaternionValue"
    },
    {
        "kind": "struct/member",
        "name": "fuchsia.ui.gfx/RectangleArgs.height",
        "type": "fuchsia.ui.gfx/Value"
    },
    {
        "kind": "struct/member",
        "name": "fuchsia.ui.gfx/RectangleArgs.width",
        "type": "fuchsia.ui.gfx/Value"
    },
    {
        "kind": "struct",
        "name": "fuchsia.ui.gfx/RectangleArgs"
    },
    {
        "kind": "struct/member",
        "name": "fuchsia.ui.gfx/ReleaseResourceCmd.id",
        "type": "uint32"
    },
    {
        "kind": "struct",
        "name": "fuchsia.ui.gfx/ReleaseResourceCmd"
    },
    {
        "kind": "struct/member",
        "name": "fuchsia.ui.gfx/RemoveAllLayersCmd.layer_stack_id",
        "type": "uint32"
    },
    {
        "kind": "struct",
        "name": "fuchsia.ui.gfx/RemoveAllLayersCmd"
    },
    {
        "kind": "struct/member",
        "name": "fuchsia.ui.gfx/RemoveLayerCmd.layer_id",
        "type": "uint32"
    },
    {
        "kind": "struct/member",
        "name": "fuchsia.ui.gfx/RemoveLayerCmd.layer_stack_id",
        "type": "uint32"
    },
    {
        "kind": "struct",
        "name": "fuchsia.ui.gfx/RemoveLayerCmd"
    },
    {
        "kind": "enum/member",
        "name": "fuchsia.ui.gfx/RenderFrequency.CONTINUOUSLY",
        "value": "1"
    },
    {
        "kind": "enum/member",
        "name": "fuchsia.ui.gfx/RenderFrequency.WHEN_REQUESTED",
        "value": "0"
    },
    {
        "kind": "enum",
        "name": "fuchsia.ui.gfx/RenderFrequency",
        "strictness": "strict",
        "type": "uint32"
    },
    {
        "kind": "struct/member",
        "name": "fuchsia.ui.gfx/RendererArgs.dummy",
        "type": "uint32",
        "value": "0"
    },
    {
        "kind": "struct",
        "name": "fuchsia.ui.gfx/RendererArgs"
    },
    {
        "kind": "union/member",
        "name": "fuchsia.ui.gfx/RendererParam.enable_debugging",
        "type": "bool"
    },
    {
        "kind": "union/member",
        "name": "fuchsia.ui.gfx/RendererParam.reserved",
        "type": "fuchsia.ui.gfx/RenderFrequency"
    },
    {
        "kind": "union/member",
        "name": "fuchsia.ui.gfx/RendererParam.shadow_technique",
        "type": "fuchsia.ui.gfx/ShadowTechnique"
    },
    {
        "kind": "union",
        "name": "fuchsia.ui.gfx/RendererParam",
        "strictness": "strict"
    },
    {
        "kind": "union/member",
        "name": "fuchsia.ui.gfx/ResourceArgs.ambient_light",
        "type": "fuchsia.ui.gfx/AmbientLightArgs"
    },
    {
        "kind": "union/member",
        "name": "fuchsia.ui.gfx/ResourceArgs.buffer",
        "type": "fuchsia.ui.gfx/BufferArgs"
    },
    {
        "kind": "union/member",
        "name": "fuchsia.ui.gfx/ResourceArgs.camera",
        "type": "fuchsia.ui.gfx/CameraArgs"
    },
    {
        "kind": "union/member",
        "name": "fuchsia.ui.gfx/ResourceArgs.circle",
        "type": "fuchsia.ui.gfx/CircleArgs"
    },
    {
        "kind": "union/member",
        "name": "fuchsia.ui.gfx/ResourceArgs.clip_node",
        "type": "fuchsia.ui.gfx/ClipNodeArgs"
    },
    {
        "kind": "union/member",
        "name": "fuchsia.ui.gfx/ResourceArgs.compositor",
        "type": "fuchsia.ui.gfx/CompositorArgs"
    },
    {
        "kind": "union/member",
        "name": "fuchsia.ui.gfx/ResourceArgs.directional_light",
        "type": "fuchsia.ui.gfx/DirectionalLightArgs"
    },
    {
        "kind": "union/member",
        "name": "fuchsia.ui.gfx/ResourceArgs.display_compositor",
        "type": "fuchsia.ui.gfx/DisplayCompositorArgs"
    },
    {
        "kind": "union/member",
        "name": "fuchsia.ui.gfx/ResourceArgs.entity_node",
        "type": "fuchsia.ui.gfx/EntityNodeArgs"
    },
    {
        "kind": "union/member",
        "name": "fuchsia.ui.gfx/ResourceArgs.image",
        "type": "fuchsia.ui.gfx/ImageArgs"
    },
    {
        "kind": "union/member",
        "name": "fuchsia.ui.gfx/ResourceArgs.image2",
        "type": "fuchsia.ui.gfx/ImageArgs2"
    },
    {
        "kind": "union/member",
        "name": "fuchsia.ui.gfx/ResourceArgs.image3",
        "type": "fuchsia.ui.gfx/ImageArgs3"
    },
    {
        "kind": "union/member",
        "name": "fuchsia.ui.gfx/ResourceArgs.image_pipe2",
        "type": "fuchsia.ui.gfx/ImagePipe2Args"
    },
    {
        "kind": "union/member",
        "name": "fuchsia.ui.gfx/ResourceArgs.layer",
        "type": "fuchsia.ui.gfx/LayerArgs"
    },
    {
        "kind": "union/member",
        "name": "fuchsia.ui.gfx/ResourceArgs.layer_stack",
        "type": "fuchsia.ui.gfx/LayerStackArgs"
    },
    {
        "kind": "union/member",
        "name": "fuchsia.ui.gfx/ResourceArgs.material",
        "type": "fuchsia.ui.gfx/MaterialArgs"
    },
    {
        "kind": "union/member",
        "name": "fuchsia.ui.gfx/ResourceArgs.memory",
        "type": "fuchsia.ui.gfx/MemoryArgs"
    },
    {
        "kind": "union/member",
        "name": "fuchsia.ui.gfx/ResourceArgs.mesh",
        "type": "fuchsia.ui.gfx/MeshArgs"
    },
    {
        "kind": "union/member",
        "name": "fuchsia.ui.gfx/ResourceArgs.opacity_node",
        "type": "fuchsia.ui.gfx/OpacityNodeArgsHACK"
    },
    {
        "kind": "union/member",
        "name": "fuchsia.ui.gfx/ResourceArgs.point_light",
        "type": "fuchsia.ui.gfx/PointLightArgs"
    },
    {
        "kind": "union/member",
        "name": "fuchsia.ui.gfx/ResourceArgs.rectangle",
        "type": "fuchsia.ui.gfx/RectangleArgs"
    },
    {
        "kind": "union/member",
        "name": "fuchsia.ui.gfx/ResourceArgs.renderer",
        "type": "fuchsia.ui.gfx/RendererArgs"
    },
    {
        "kind": "union/member",
        "name": "fuchsia.ui.gfx/ResourceArgs.rounded_rectangle",
        "type": "fuchsia.ui.gfx/RoundedRectangleArgs"
    },
    {
        "kind": "union/member",
        "name": "fuchsia.ui.gfx/ResourceArgs.scene",
        "type": "fuchsia.ui.gfx/SceneArgs"
    },
    {
        "kind": "union/member",
        "name": "fuchsia.ui.gfx/ResourceArgs.shape_node",
        "type": "fuchsia.ui.gfx/ShapeNodeArgs"
    },
    {
        "kind": "union/member",
        "name": "fuchsia.ui.gfx/ResourceArgs.stereo_camera",
        "type": "fuchsia.ui.gfx/StereoCameraArgs"
    },
    {
        "kind": "union/member",
        "name": "fuchsia.ui.gfx/ResourceArgs.variable",
        "type": "fuchsia.ui.gfx/VariableArgs"
    },
    {
        "kind": "union/member",
        "name": "fuchsia.ui.gfx/ResourceArgs.view",
        "type": "fuchsia.ui.gfx/ViewArgs"
    },
    {
        "kind": "union/member",
        "name": "fuchsia.ui.gfx/ResourceArgs.view3",
        "type": "fuchsia.ui.gfx/ViewArgs3"
    },
    {
        "kind": "union/member",
        "name": "fuchsia.ui.gfx/ResourceArgs.view_holder",
        "type": "fuchsia.ui.gfx/ViewHolderArgs"
    },
    {
        "kind": "union",
        "name": "fuchsia.ui.gfx/ResourceArgs",
        "resourceness": "resource",
        "strictness": "strict"
    },
    {
        "kind": "struct/member",
        "name": "fuchsia.ui.gfx/RoundedRectangleArgs.bottom_left_radius",
        "type": "fuchsia.ui.gfx/Value"
    },
    {
        "kind": "struct/member",
        "name": "fuchsia.ui.gfx/RoundedRectangleArgs.bottom_right_radius",
        "type": "fuchsia.ui.gfx/Value"
    },
    {
        "kind": "struct/member",
        "name": "fuchsia.ui.gfx/RoundedRectangleArgs.height",
        "type": "fuchsia.ui.gfx/Value"
    },
    {
        "kind": "struct/member",
        "name": "fuchsia.ui.gfx/RoundedRectangleArgs.top_left_radius",
        "type": "fuchsia.ui.gfx/Value"
    },
    {
        "kind": "struct/member",
        "name": "fuchsia.ui.gfx/RoundedRectangleArgs.top_right_radius",
        "type": "fuchsia.ui.gfx/Value"
    },
    {
        "kind": "struct/member",
        "name": "fuchsia.ui.gfx/RoundedRectangleArgs.width",
        "type": "fuchsia.ui.gfx/Value"
    },
    {
        "kind": "struct",
        "name": "fuchsia.ui.gfx/RoundedRectangleArgs"
    },
    {
        "kind": "struct/member",
        "name": "fuchsia.ui.gfx/SceneAddAmbientLightCmd.light_id",
        "type": "uint32"
    },
    {
        "kind": "struct/member",
        "name": "fuchsia.ui.gfx/SceneAddAmbientLightCmd.scene_id",
        "type": "uint32"
    },
    {
        "kind": "struct",
        "name": "fuchsia.ui.gfx/SceneAddAmbientLightCmd"
    },
    {
        "kind": "struct/member",
        "name": "fuchsia.ui.gfx/SceneAddDirectionalLightCmd.light_id",
        "type": "uint32"
    },
    {
        "kind": "struct/member",
        "name": "fuchsia.ui.gfx/SceneAddDirectionalLightCmd.scene_id",
        "type": "uint32"
    },
    {
        "kind": "struct",
        "name": "fuchsia.ui.gfx/SceneAddDirectionalLightCmd"
    },
    {
        "kind": "struct/member",
        "name": "fuchsia.ui.gfx/SceneAddPointLightCmd.light_id",
        "type": "uint32"
    },
    {
        "kind": "struct/member",
        "name": "fuchsia.ui.gfx/SceneAddPointLightCmd.scene_id",
        "type": "uint32"
    },
    {
        "kind": "struct",
        "name": "fuchsia.ui.gfx/SceneAddPointLightCmd"
    },
    {
        "kind": "struct/member",
        "name": "fuchsia.ui.gfx/SceneArgs.dummy",
        "type": "uint32",
        "value": "0"
    },
    {
        "kind": "struct",
        "name": "fuchsia.ui.gfx/SceneArgs"
    },
    {
        "kind": "struct/member",
        "name": "fuchsia.ui.gfx/SendSizeChangeHintCmdHACK.height_change_factor",
        "type": "float32"
    },
    {
        "kind": "struct/member",
        "name": "fuchsia.ui.gfx/SendSizeChangeHintCmdHACK.node_id",
        "type": "uint32"
    },
    {
        "kind": "struct/member",
        "name": "fuchsia.ui.gfx/SendSizeChangeHintCmdHACK.width_change_factor",
        "type": "float32"
    },
    {
        "kind": "struct",
        "name": "fuchsia.ui.gfx/SendSizeChangeHintCmdHACK"
    },
    {
        "kind": "struct/member",
        "name": "fuchsia.ui.gfx/SetAnchorCmd.id",
        "type": "uint32"
    },
    {
        "kind": "struct/member",
        "name": "fuchsia.ui.gfx/SetAnchorCmd.value",
        "type": "fuchsia.ui.gfx/Vector3Value"
    },
    {
        "kind": "struct",
        "name": "fuchsia.ui.gfx/SetAnchorCmd"
    },
    {
        "kind": "struct/member",
        "name": "fuchsia.ui.gfx/SetCameraClipSpaceTransformCmd.camera_id",
        "type": "uint32"
    },
    {
        "kind": "struct/member",
        "name": "fuchsia.ui.gfx/SetCameraClipSpaceTransformCmd.scale",
        "type": "float32"
    },
    {
        "kind": "struct/member",
        "name": "fuchsia.ui.gfx/SetCameraClipSpaceTransformCmd.translation",
        "type": "fuchsia.ui.gfx/vec2"
    },
    {
        "kind": "struct",
        "name": "fuchsia.ui.gfx/SetCameraClipSpaceTransformCmd"
    },
    {
        "kind": "struct/member",
        "name": "fuchsia.ui.gfx/SetCameraCmd.camera_id",
        "type": "uint32"
    },
    {
        "kind": "struct/member",
        "name": "fuchsia.ui.gfx/SetCameraCmd.renderer_id",
        "type": "uint32"
    },
    {
        "kind": "struct",
        "name": "fuchsia.ui.gfx/SetCameraCmd"
    },
    {
        "kind": "struct/member",
        "name": "fuchsia.ui.gfx/SetCameraPoseBufferCmd.base_time",
        "type": "int64"
    },
    {
        "kind": "struct/member",
        "name": "fuchsia.ui.gfx/SetCameraPoseBufferCmd.buffer_id",
        "type": "uint32"
    },
    {
        "kind": "struct/member",
        "name": "fuchsia.ui.gfx/SetCameraPoseBufferCmd.camera_id",
        "type": "uint32"
    },
    {
        "kind": "struct/member",
        "name": "fuchsia.ui.gfx/SetCameraPoseBufferCmd.num_entries",
        "type": "uint32"
    },
    {
        "kind": "struct/member",
        "name": "fuchsia.ui.gfx/SetCameraPoseBufferCmd.time_interval",
        "type": "uint64"
    },
    {
        "kind": "struct",
        "name": "fuchsia.ui.gfx/SetCameraPoseBufferCmd"
    },
    {
        "kind": "struct/member",
        "name": "fuchsia.ui.gfx/SetCameraProjectionCmd.camera_id",
        "type": "uint32"
    },
    {
        "kind": "struct/member",
        "name": "fuchsia.ui.gfx/SetCameraProjectionCmd.fovy",
        "type": "fuchsia.ui.gfx/FloatValue"
    },
    {
        "kind": "struct",
        "name": "fuchsia.ui.gfx/SetCameraProjectionCmd"
    },
    {
        "kind": "struct/member",
        "name": "fuchsia.ui.gfx/SetCameraTransformCmd.camera_id",
        "type": "uint32"
    },
    {
        "kind": "struct/member",
        "name": "fuchsia.ui.gfx/SetCameraTransformCmd.eye_look_at",
        "type": "fuchsia.ui.gfx/Vector3Value"
    },
    {
        "kind": "struct/member",
        "name": "fuchsia.ui.gfx/SetCameraTransformCmd.eye_position",
        "type": "fuchsia.ui.gfx/Vector3Value"
    },
    {
        "kind": "struct/member",
        "name": "fuchsia.ui.gfx/SetCameraTransformCmd.eye_up",
        "type": "fuchsia.ui.gfx/Vector3Value"
    },
    {
        "kind": "struct",
        "name": "fuchsia.ui.gfx/SetCameraTransformCmd"
    },
    {
        "kind": "struct/member",
        "name": "fuchsia.ui.gfx/SetClipCmd.clip_id",
        "type": "uint32"
    },
    {
        "kind": "struct/member",
        "name": "fuchsia.ui.gfx/SetClipCmd.clip_to_self",
        "type": "bool"
    },
    {
        "kind": "struct/member",
        "name": "fuchsia.ui.gfx/SetClipCmd.node_id",
        "type": "uint32"
    },
    {
        "kind": "struct",
        "name": "fuchsia.ui.gfx/SetClipCmd"
    },
    {
        "kind": "struct/member",
        "name": "fuchsia.ui.gfx/SetClipPlanesCmd.clip_planes",
        "type": "vector<fuchsia.ui.gfx/Plane3>"
    },
    {
        "kind": "struct/member",
        "name": "fuchsia.ui.gfx/SetClipPlanesCmd.node_id",
        "type": "uint32"
    },
    {
        "kind": "struct",
        "name": "fuchsia.ui.gfx/SetClipPlanesCmd"
    },
    {
        "kind": "struct/member",
        "name": "fuchsia.ui.gfx/SetColorCmd.color",
        "type": "fuchsia.ui.gfx/ColorRgbaValue"
    },
    {
        "kind": "struct/member",
        "name": "fuchsia.ui.gfx/SetColorCmd.material_id",
        "type": "uint32"
    },
    {
        "kind": "struct",
        "name": "fuchsia.ui.gfx/SetColorCmd"
    },
    {
        "kind": "struct/member",
        "name": "fuchsia.ui.gfx/SetDisableClippingCmd.disable_clipping",
        "type": "bool"
    },
    {
        "kind": "struct/member",
        "name": "fuchsia.ui.gfx/SetDisableClippingCmd.renderer_id",
        "type": "uint32"
    },
    {
        "kind": "struct",
        "name": "fuchsia.ui.gfx/SetDisableClippingCmd"
    },
    {
        "kind": "struct/member",
        "name": "fuchsia.ui.gfx/SetDisplayColorConversionCmdHACK.compositor_id",
        "type": "uint32"
    },
    {
        "kind": "struct/member",
        "name": "fuchsia.ui.gfx/SetDisplayColorConversionCmdHACK.matrix",
        "type": "array<float32,9>"
    },
    {
        "kind": "struct/member",
        "name": "fuchsia.ui.gfx/SetDisplayColorConversionCmdHACK.postoffsets",
        "type": "array<float32,3>"
    },
    {
        "kind": "struct/member",
        "name": "fuchsia.ui.gfx/SetDisplayColorConversionCmdHACK.preoffsets",
        "type": "array<float32,3>"
    },
    {
        "kind": "struct",
        "name": "fuchsia.ui.gfx/SetDisplayColorConversionCmdHACK"
    },
    {
        "kind": "struct/member",
        "name": "fuchsia.ui.gfx/SetDisplayMinimumRgbCmdHACK.min_value",
        "type": "uint8"
    },
    {
        "kind": "struct",
        "name": "fuchsia.ui.gfx/SetDisplayMinimumRgbCmdHACK"
    },
    {
        "kind": "struct/member",
        "name": "fuchsia.ui.gfx/SetDisplayRotationCmdHACK.compositor_id",
        "type": "uint32"
    },
    {
        "kind": "struct/member",
        "name": "fuchsia.ui.gfx/SetDisplayRotationCmdHACK.rotation_degrees",
        "type": "uint32"
    },
    {
        "kind": "struct",
        "name": "fuchsia.ui.gfx/SetDisplayRotationCmdHACK"
    },
    {
        "kind": "struct/member",
        "name": "fuchsia.ui.gfx/SetEnableDebugViewBoundsCmd.enable",
        "type": "bool"
    },
    {
        "kind": "struct/member",
        "name": "fuchsia.ui.gfx/SetEnableDebugViewBoundsCmd.view_id",
        "type": "uint32"
    },
    {
        "kind": "struct",
        "name": "fuchsia.ui.gfx/SetEnableDebugViewBoundsCmd"
    },
    {
        "kind": "struct/member",
        "name": "fuchsia.ui.gfx/SetEventMaskCmd.event_mask",
        "type": "uint32"
    },
    {
        "kind": "struct/member",
        "name": "fuchsia.ui.gfx/SetEventMaskCmd.id",
        "type": "uint32"
    },
    {
        "kind": "struct",
        "name": "fuchsia.ui.gfx/SetEventMaskCmd"
    },
    {
        "kind": "struct/member",
        "name": "fuchsia.ui.gfx/SetHitTestBehaviorCmd.hit_test_behavior",
        "type": "fuchsia.ui.gfx/HitTestBehavior"
    },
    {
        "kind": "struct/member",
        "name": "fuchsia.ui.gfx/SetHitTestBehaviorCmd.node_id",
        "type": "uint32"
    },
    {
        "kind": "struct",
        "name": "fuchsia.ui.gfx/SetHitTestBehaviorCmd"
    },
    {
        "kind": "struct",
        "name": "fuchsia.ui.gfx/SetImportFocusCmdDEPRECATED"
    },
    {
        "kind": "struct/member",
        "name": "fuchsia.ui.gfx/SetLabelCmd.id",
        "type": "uint32"
    },
    {
        "kind": "struct/member",
        "name": "fuchsia.ui.gfx/SetLabelCmd.label",
        "type": "string"
    },
    {
        "kind": "struct",
        "name": "fuchsia.ui.gfx/SetLabelCmd"
    },
    {
        "kind": "struct/member",
        "name": "fuchsia.ui.gfx/SetLayerStackCmd.compositor_id",
        "type": "uint32"
    },
    {
        "kind": "struct/member",
        "name": "fuchsia.ui.gfx/SetLayerStackCmd.layer_stack_id",
        "type": "uint32"
    },
    {
        "kind": "struct",
        "name": "fuchsia.ui.gfx/SetLayerStackCmd"
    },
    {
        "kind": "struct/member",
        "name": "fuchsia.ui.gfx/SetLightColorCmd.color",
        "type": "fuchsia.ui.gfx/ColorRgbValue"
    },
    {
        "kind": "struct/member",
        "name": "fuchsia.ui.gfx/SetLightColorCmd.light_id",
        "type": "uint32"
    },
    {
        "kind": "struct",
        "name": "fuchsia.ui.gfx/SetLightColorCmd"
    },
    {
        "kind": "struct/member",
        "name": "fuchsia.ui.gfx/SetLightDirectionCmd.direction",
        "type": "fuchsia.ui.gfx/Vector3Value"
    },
    {
        "kind": "struct/member",
        "name": "fuchsia.ui.gfx/SetLightDirectionCmd.light_id",
        "type": "uint32"
    },
    {
        "kind": "struct",
        "name": "fuchsia.ui.gfx/SetLightDirectionCmd"
    },
    {
        "kind": "struct/member",
        "name": "fuchsia.ui.gfx/SetMaterialCmd.material_id",
        "type": "uint32"
    },
    {
        "kind": "struct/member",
        "name": "fuchsia.ui.gfx/SetMaterialCmd.node_id",
        "type": "uint32"
    },
    {
        "kind": "struct",
        "name": "fuchsia.ui.gfx/SetMaterialCmd"
    },
    {
        "kind": "struct/member",
        "name": "fuchsia.ui.gfx/SetOpacityCmd.node_id",
        "type": "uint32"
    },
    {
        "kind": "struct/member",
        "name": "fuchsia.ui.gfx/SetOpacityCmd.opacity",
        "type": "float32"
    },
    {
        "kind": "struct",
        "name": "fuchsia.ui.gfx/SetOpacityCmd"
    },
    {
        "kind": "struct/member",
        "name": "fuchsia.ui.gfx/SetPointLightFalloffCmd.falloff",
        "type": "fuchsia.ui.gfx/FloatValue"
    },
    {
        "kind": "struct/member",
        "name": "fuchsia.ui.gfx/SetPointLightFalloffCmd.light_id",
        "type": "uint32"
    },
    {
        "kind": "struct",
        "name": "fuchsia.ui.gfx/SetPointLightFalloffCmd"
    },
    {
        "kind": "struct/member",
        "name": "fuchsia.ui.gfx/SetPointLightPositionCmd.light_id",
        "type": "uint32"
    },
    {
        "kind": "struct/member",
        "name": "fuchsia.ui.gfx/SetPointLightPositionCmd.position",
        "type": "fuchsia.ui.gfx/Vector3Value"
    },
    {
        "kind": "struct",
        "name": "fuchsia.ui.gfx/SetPointLightPositionCmd"
    },
    {
        "kind": "struct/member",
        "name": "fuchsia.ui.gfx/SetRendererCmd.layer_id",
        "type": "uint32"
    },
    {
        "kind": "struct/member",
        "name": "fuchsia.ui.gfx/SetRendererCmd.renderer_id",
        "type": "uint32"
    },
    {
        "kind": "struct",
        "name": "fuchsia.ui.gfx/SetRendererCmd"
    },
    {
        "kind": "struct/member",
        "name": "fuchsia.ui.gfx/SetRendererParamCmd.param",
        "type": "fuchsia.ui.gfx/RendererParam"
    },
    {
        "kind": "struct/member",
        "name": "fuchsia.ui.gfx/SetRendererParamCmd.renderer_id",
        "type": "uint32"
    },
    {
        "kind": "struct",
        "name": "fuchsia.ui.gfx/SetRendererParamCmd"
    },
    {
        "kind": "struct/member",
        "name": "fuchsia.ui.gfx/SetRotationCmd.id",
        "type": "uint32"
    },
    {
        "kind": "struct/member",
        "name": "fuchsia.ui.gfx/SetRotationCmd.value",
        "type": "fuchsia.ui.gfx/QuaternionValue"
    },
    {
        "kind": "struct",
        "name": "fuchsia.ui.gfx/SetRotationCmd"
    },
    {
        "kind": "struct/member",
        "name": "fuchsia.ui.gfx/SetScaleCmd.id",
        "type": "uint32"
    },
    {
        "kind": "struct/member",
        "name": "fuchsia.ui.gfx/SetScaleCmd.value",
        "type": "fuchsia.ui.gfx/Vector3Value"
    },
    {
        "kind": "struct",
        "name": "fuchsia.ui.gfx/SetScaleCmd"
    },
    {
        "kind": "struct/member",
        "name": "fuchsia.ui.gfx/SetSemanticVisibilityCmd.node_id",
        "type": "uint32"
    },
    {
        "kind": "struct/member",
        "name": "fuchsia.ui.gfx/SetSemanticVisibilityCmd.visible",
        "type": "bool",
        "value": "true"
    },
    {
        "kind": "struct",
        "name": "fuchsia.ui.gfx/SetSemanticVisibilityCmd"
    },
    {
        "kind": "struct/member",
        "name": "fuchsia.ui.gfx/SetShapeCmd.node_id",
        "type": "uint32"
    },
    {
        "kind": "struct/member",
        "name": "fuchsia.ui.gfx/SetShapeCmd.shape_id",
        "type": "uint32"
    },
    {
        "kind": "struct",
        "name": "fuchsia.ui.gfx/SetShapeCmd"
    },
    {
        "kind": "struct/member",
        "name": "fuchsia.ui.gfx/SetSizeCmd.id",
        "type": "uint32"
    },
    {
        "kind": "struct/member",
        "name": "fuchsia.ui.gfx/SetSizeCmd.value",
        "type": "fuchsia.ui.gfx/Vector2Value"
    },
    {
        "kind": "struct",
        "name": "fuchsia.ui.gfx/SetSizeCmd"
    },
    {
        "kind": "struct/member",
        "name": "fuchsia.ui.gfx/SetStereoCameraProjectionCmd.camera_id",
        "type": "uint32"
    },
    {
        "kind": "struct/member",
        "name": "fuchsia.ui.gfx/SetStereoCameraProjectionCmd.left_projection",
        "type": "fuchsia.ui.gfx/Matrix4Value"
    },
    {
        "kind": "struct/member",
        "name": "fuchsia.ui.gfx/SetStereoCameraProjectionCmd.right_projection",
        "type": "fuchsia.ui.gfx/Matrix4Value"
    },
    {
        "kind": "struct",
        "name": "fuchsia.ui.gfx/SetStereoCameraProjectionCmd"
    },
    {
        "kind": "struct/member",
        "name": "fuchsia.ui.gfx/SetTagCmd.node_id",
        "type": "uint32"
    },
    {
        "kind": "struct/member",
        "name": "fuchsia.ui.gfx/SetTagCmd.tag_value",
        "type": "uint32"
    },
    {
        "kind": "struct",
        "name": "fuchsia.ui.gfx/SetTagCmd"
    },
    {
        "kind": "struct/member",
        "name": "fuchsia.ui.gfx/SetTextureCmd.material_id",
        "type": "uint32"
    },
    {
        "kind": "struct/member",
        "name": "fuchsia.ui.gfx/SetTextureCmd.texture_id",
        "type": "uint32"
    },
    {
        "kind": "struct",
        "name": "fuchsia.ui.gfx/SetTextureCmd"
    },
    {
        "kind": "struct/member",
        "name": "fuchsia.ui.gfx/SetTranslationCmd.id",
        "type": "uint32"
    },
    {
        "kind": "struct/member",
        "name": "fuchsia.ui.gfx/SetTranslationCmd.value",
        "type": "fuchsia.ui.gfx/Vector3Value"
    },
    {
        "kind": "struct",
        "name": "fuchsia.ui.gfx/SetTranslationCmd"
    },
    {
        "kind": "struct/member",
        "name": "fuchsia.ui.gfx/SetViewHolderBoundsColorCmd.color",
        "type": "fuchsia.ui.gfx/ColorRgbValue"
    },
    {
        "kind": "struct/member",
        "name": "fuchsia.ui.gfx/SetViewHolderBoundsColorCmd.view_holder_id",
        "type": "uint32"
    },
    {
        "kind": "struct",
        "name": "fuchsia.ui.gfx/SetViewHolderBoundsColorCmd"
    },
    {
        "kind": "struct/member",
        "name": "fuchsia.ui.gfx/SetViewPropertiesCmd.properties",
        "type": "fuchsia.ui.gfx/ViewProperties"
    },
    {
        "kind": "struct/member",
        "name": "fuchsia.ui.gfx/SetViewPropertiesCmd.view_holder_id",
        "type": "uint32"
    },
    {
        "kind": "struct",
        "name": "fuchsia.ui.gfx/SetViewPropertiesCmd"
    },
    {
        "kind": "enum/member",
        "name": "fuchsia.ui.gfx/ShadowTechnique.MOMENT_SHADOW_MAP",
        "value": "3"
    },
    {
        "kind": "enum/member",
        "name": "fuchsia.ui.gfx/ShadowTechnique.SCREEN_SPACE",
        "value": "1"
    },
    {
        "kind": "enum/member",
        "name": "fuchsia.ui.gfx/ShadowTechnique.SHADOW_MAP",
        "value": "2"
    },
    {
        "kind": "enum/member",
        "name": "fuchsia.ui.gfx/ShadowTechnique.STENCIL_SHADOW_VOLUME",
        "value": "4"
    },
    {
        "kind": "enum/member",
        "name": "fuchsia.ui.gfx/ShadowTechnique.UNSHADOWED",
        "value": "0"
    },
    {
        "kind": "enum",
        "name": "fuchsia.ui.gfx/ShadowTechnique",
        "strictness": "strict",
        "type": "uint32"
    },
    {
        "kind": "struct/member",
        "name": "fuchsia.ui.gfx/ShapeNodeArgs.unused",
        "type": "uint32",
        "value": "0"
    },
    {
        "kind": "struct",
        "name": "fuchsia.ui.gfx/ShapeNodeArgs"
    },
    {
        "kind": "struct/member",
        "name": "fuchsia.ui.gfx/SizeChangeHintEvent.height_change_factor",
        "type": "float32"
    },
    {
        "kind": "struct/member",
        "name": "fuchsia.ui.gfx/SizeChangeHintEvent.node_id",
        "type": "uint32"
    },
    {
        "kind": "struct/member",
        "name": "fuchsia.ui.gfx/SizeChangeHintEvent.width_change_factor",
        "type": "float32"
    },
    {
        "kind": "struct",
        "name": "fuchsia.ui.gfx/SizeChangeHintEvent"
    },
    {
        "kind": "protocol/member",
        "name": "fuchsia.ui.gfx/SnapshotCallbackDEPRECATED.OnData",
        "type": "(fuchsia.mem/Buffer data)"
    },
    {
        "kind": "protocol",
        "name": "fuchsia.ui.gfx/SnapshotCallbackDEPRECATED"
    },
    {
        "kind": "struct/member",
        "name": "fuchsia.ui.gfx/StereoCameraArgs.scene_id",
        "type": "uint32"
    },
    {
        "kind": "struct",
        "name": "fuchsia.ui.gfx/StereoCameraArgs"
    },
    {
        "kind": "struct/member",
        "name": "fuchsia.ui.gfx/TakeSnapshotCmdDEPRECATED.callback",
        "type": "client_end:fuchsia.ui.gfx/SnapshotCallbackDEPRECATED"
    },
    {
        "kind": "struct/member",
        "name": "fuchsia.ui.gfx/TakeSnapshotCmdDEPRECATED.node_id",
        "type": "uint32"
    },
    {
        "kind": "struct",
        "name": "fuchsia.ui.gfx/TakeSnapshotCmdDEPRECATED",
        "resourceness": "resource"
    },
    {
        "kind": "union/member",
        "name": "fuchsia.ui.gfx/Value.color_rgb",
        "type": "fuchsia.ui.gfx/ColorRgb"
    },
    {
        "kind": "union/member",
        "name": "fuchsia.ui.gfx/Value.color_rgba",
        "type": "fuchsia.ui.gfx/ColorRgba"
    },
    {
        "kind": "union/member",
        "name": "fuchsia.ui.gfx/Value.degrees",
        "type": "float32"
    },
    {
        "kind": "union/member",
        "name": "fuchsia.ui.gfx/Value.matrix4x4",
        "type": "fuchsia.ui.gfx/mat4"
    },
    {
        "kind": "union/member",
        "name": "fuchsia.ui.gfx/Value.quaternion",
        "type": "fuchsia.ui.gfx/Quaternion"
    },
    {
        "kind": "union/member",
        "name": "fuchsia.ui.gfx/Value.transform",
        "type": "fuchsia.ui.gfx/FactoredTransform"
    },
    {
        "kind": "union/member",
        "name": "fuchsia.ui.gfx/Value.variable_id",
        "type": "uint32"
    },
    {
        "kind": "union/member",
        "name": "fuchsia.ui.gfx/Value.vector1",
        "type": "float32"
    },
    {
        "kind": "union/member",
        "name": "fuchsia.ui.gfx/Value.vector2",
        "type": "fuchsia.ui.gfx/vec2"
    },
    {
        "kind": "union/member",
        "name": "fuchsia.ui.gfx/Value.vector3",
        "type": "fuchsia.ui.gfx/vec3"
    },
    {
        "kind": "union/member",
        "name": "fuchsia.ui.gfx/Value.vector4",
        "type": "fuchsia.ui.gfx/vec4"
    },
    {
        "kind": "union",
        "name": "fuchsia.ui.gfx/Value",
        "strictness": "strict"
    },
    {
        "kind": "enum/member",
        "name": "fuchsia.ui.gfx/ValueType.kColorRgb",
        "value": "6"
    },
    {
        "kind": "enum/member",
        "name": "fuchsia.ui.gfx/ValueType.kColorRgba",
        "value": "7"
    },
    {
        "kind": "enum/member",
        "name": "fuchsia.ui.gfx/ValueType.kFactoredTransform",
        "value": "9"
    },
    {
        "kind": "enum/member",
        "name": "fuchsia.ui.gfx/ValueType.kMatrix4",
        "value": "5"
    },
    {
        "kind": "enum/member",
        "name": "fuchsia.ui.gfx/ValueType.kNone",
        "value": "0"
    },
    {
        "kind": "enum/member",
        "name": "fuchsia.ui.gfx/ValueType.kQuaternion",
        "value": "8"
    },
    {
        "kind": "enum/member",
        "name": "fuchsia.ui.gfx/ValueType.kVector1",
        "value": "1"
    },
    {
        "kind": "enum/member",
        "name": "fuchsia.ui.gfx/ValueType.kVector2",
        "value": "2"
    },
    {
        "kind": "enum/member",
        "name": "fuchsia.ui.gfx/ValueType.kVector3",
        "value": "3"
    },
    {
        "kind": "enum/member",
        "name": "fuchsia.ui.gfx/ValueType.kVector4",
        "value": "4"
    },
    {
        "kind": "enum",
        "name": "fuchsia.ui.gfx/ValueType",
        "strictness": "strict",
        "type": "uint32"
    },
    {
        "kind": "struct/member",
        "name": "fuchsia.ui.gfx/VariableArgs.initial_value",
        "type": "fuchsia.ui.gfx/Value"
    },
    {
        "kind": "struct/member",
        "name": "fuchsia.ui.gfx/VariableArgs.type",
        "type": "fuchsia.ui.gfx/ValueType"
    },
    {
        "kind": "struct",
        "name": "fuchsia.ui.gfx/VariableArgs"
    },
    {
        "kind": "struct/member",
        "name": "fuchsia.ui.gfx/Vector2Value.value",
        "type": "fuchsia.ui.gfx/vec2"
    },
    {
        "kind": "struct/member",
        "name": "fuchsia.ui.gfx/Vector2Value.variable_id",
        "type": "uint32"
    },
    {
        "kind": "struct",
        "name": "fuchsia.ui.gfx/Vector2Value"
    },
    {
        "kind": "struct/member",
        "name": "fuchsia.ui.gfx/Vector3Value.value",
        "type": "fuchsia.ui.gfx/vec3"
    },
    {
        "kind": "struct/member",
        "name": "fuchsia.ui.gfx/Vector3Value.variable_id",
        "type": "uint32"
    },
    {
        "kind": "struct",
        "name": "fuchsia.ui.gfx/Vector3Value"
    },
    {
        "kind": "struct/member",
        "name": "fuchsia.ui.gfx/Vector4Value.value",
        "type": "fuchsia.ui.gfx/vec4"
    },
    {
        "kind": "struct/member",
        "name": "fuchsia.ui.gfx/Vector4Value.variable_id",
        "type": "uint32"
    },
    {
        "kind": "struct",
        "name": "fuchsia.ui.gfx/Vector4Value"
    },
    {
        "kind": "struct/member",
        "name": "fuchsia.ui.gfx/ViewArgs.debug_name",
        "type": "string:optional"
    },
    {
        "kind": "struct/member",
        "name": "fuchsia.ui.gfx/ViewArgs.token",
        "type": "fuchsia.ui.views/ViewToken"
    },
    {
        "kind": "struct",
        "name": "fuchsia.ui.gfx/ViewArgs",
        "resourceness": "resource"
    },
    {
        "kind": "struct/member",
        "name": "fuchsia.ui.gfx/ViewArgs3.control_ref",
        "type": "fuchsia.ui.views/ViewRefControl"
    },
    {
        "kind": "struct/member",
        "name": "fuchsia.ui.gfx/ViewArgs3.debug_name",
        "type": "string:optional"
    },
    {
        "kind": "struct/member",
        "name": "fuchsia.ui.gfx/ViewArgs3.token",
        "type": "fuchsia.ui.views/ViewToken"
    },
    {
        "kind": "struct/member",
        "name": "fuchsia.ui.gfx/ViewArgs3.view_ref",
        "type": "fuchsia.ui.views/ViewRef"
    },
    {
        "kind": "struct",
        "name": "fuchsia.ui.gfx/ViewArgs3",
        "resourceness": "resource"
    },
    {
        "kind": "struct/member",
        "name": "fuchsia.ui.gfx/ViewAttachedToSceneEvent.properties",
        "type": "fuchsia.ui.gfx/ViewProperties"
    },
    {
        "kind": "struct/member",
        "name": "fuchsia.ui.gfx/ViewAttachedToSceneEvent.view_id",
        "type": "uint32"
    },
    {
        "kind": "struct",
        "name": "fuchsia.ui.gfx/ViewAttachedToSceneEvent"
    },
    {
        "kind": "struct/member",
        "name": "fuchsia.ui.gfx/ViewConnectedEvent.view_holder_id",
        "type": "uint32"
    },
    {
        "kind": "struct",
        "name": "fuchsia.ui.gfx/ViewConnectedEvent"
    },
    {
        "kind": "struct/member",
        "name": "fuchsia.ui.gfx/ViewDetachedFromSceneEvent.view_id",
        "type": "uint32"
    },
    {
        "kind": "struct",
        "name": "fuchsia.ui.gfx/ViewDetachedFromSceneEvent"
    },
    {
        "kind": "struct/member",
        "name": "fuchsia.ui.gfx/ViewDisconnectedEvent.view_holder_id",
        "type": "uint32"
    },
    {
        "kind": "struct",
        "name": "fuchsia.ui.gfx/ViewDisconnectedEvent"
    },
    {
        "kind": "struct/member",
        "name": "fuchsia.ui.gfx/ViewHolderArgs.debug_name",
        "type": "string:optional"
    },
    {
        "kind": "struct/member",
        "name": "fuchsia.ui.gfx/ViewHolderArgs.token",
        "type": "fuchsia.ui.views/ViewHolderToken"
    },
    {
        "kind": "struct",
        "name": "fuchsia.ui.gfx/ViewHolderArgs",
        "resourceness": "resource"
    },
    {
        "kind": "struct/member",
        "name": "fuchsia.ui.gfx/ViewHolderConnectedEvent.view_id",
        "type": "uint32"
    },
    {
        "kind": "struct",
        "name": "fuchsia.ui.gfx/ViewHolderConnectedEvent"
    },
    {
        "kind": "struct/member",
        "name": "fuchsia.ui.gfx/ViewHolderDisconnectedEvent.view_id",
        "type": "uint32"
    },
    {
        "kind": "struct",
        "name": "fuchsia.ui.gfx/ViewHolderDisconnectedEvent"
    },
    {
        "kind": "struct/member",
        "name": "fuchsia.ui.gfx/ViewProperties.bounding_box",
        "type": "fuchsia.ui.gfx/BoundingBox"
    },
    {
        "kind": "struct/member",
        "name": "fuchsia.ui.gfx/ViewProperties.downward_input",
        "type": "bool",
        "value": "true"
    },
    {
        "kind": "struct/member",
        "name": "fuchsia.ui.gfx/ViewProperties.focus_change",
        "type": "bool",
        "value": "true"
    },
    {
        "kind": "struct/member",
        "name": "fuchsia.ui.gfx/ViewProperties.inset_from_max",
        "type": "fuchsia.ui.gfx/vec3"
    },
    {
        "kind": "struct/member",
        "name": "fuchsia.ui.gfx/ViewProperties.inset_from_min",
        "type": "fuchsia.ui.gfx/vec3"
    },
    {
        "kind": "struct",
        "name": "fuchsia.ui.gfx/ViewProperties"
    },
    {
        "kind": "struct/member",
        "name": "fuchsia.ui.gfx/ViewPropertiesChangedEvent.properties",
        "type": "fuchsia.ui.gfx/ViewProperties"
    },
    {
        "kind": "struct/member",
        "name": "fuchsia.ui.gfx/ViewPropertiesChangedEvent.view_id",
        "type": "uint32"
    },
    {
        "kind": "struct",
        "name": "fuchsia.ui.gfx/ViewPropertiesChangedEvent"
    },
    {
        "kind": "struct/member",
        "name": "fuchsia.ui.gfx/ViewState.is_rendering",
        "type": "bool"
    },
    {
        "kind": "struct",
        "name": "fuchsia.ui.gfx/ViewState"
    },
    {
        "kind": "struct/member",
        "name": "fuchsia.ui.gfx/ViewStateChangedEvent.state",
        "type": "fuchsia.ui.gfx/ViewState"
    },
    {
        "kind": "struct/member",
        "name": "fuchsia.ui.gfx/ViewStateChangedEvent.view_holder_id",
        "type": "uint32"
    },
    {
        "kind": "struct",
        "name": "fuchsia.ui.gfx/ViewStateChangedEvent"
    },
    {
        "kind": "const",
        "name": "fuchsia.ui.gfx/kLabelMaxLength",
        "type": "uint32",
        "value": "32"
    },
    {
        "kind": "const",
        "name": "fuchsia.ui.gfx/kMetricsEventMask",
        "type": "uint32",
        "value": "1"
    },
    {
        "kind": "const",
        "name": "fuchsia.ui.gfx/kSizeChangeHintEventMask",
        "type": "uint32",
        "value": "2"
    },
    {
        "kind": "struct/member",
        "name": "fuchsia.ui.gfx/mat4.matrix",
        "type": "array<float32,16>"
    },
    {
        "kind": "struct",
        "name": "fuchsia.ui.gfx/mat4"
    },
    {
        "kind": "struct/member",
        "name": "fuchsia.ui.gfx/vec2.x",
        "type": "float32"
    },
    {
        "kind": "struct/member",
        "name": "fuchsia.ui.gfx/vec2.y",
        "type": "float32"
    },
    {
        "kind": "struct",
        "name": "fuchsia.ui.gfx/vec2"
    },
    {
        "kind": "struct/member",
        "name": "fuchsia.ui.gfx/vec3.x",
        "type": "float32"
    },
    {
        "kind": "struct/member",
        "name": "fuchsia.ui.gfx/vec3.y",
        "type": "float32"
    },
    {
        "kind": "struct/member",
        "name": "fuchsia.ui.gfx/vec3.z",
        "type": "float32"
    },
    {
        "kind": "struct",
        "name": "fuchsia.ui.gfx/vec3"
    },
    {
        "kind": "struct/member",
        "name": "fuchsia.ui.gfx/vec4.w",
        "type": "float32"
    },
    {
        "kind": "struct/member",
        "name": "fuchsia.ui.gfx/vec4.x",
        "type": "float32"
    },
    {
        "kind": "struct/member",
        "name": "fuchsia.ui.gfx/vec4.y",
        "type": "float32"
    },
    {
        "kind": "struct/member",
        "name": "fuchsia.ui.gfx/vec4.z",
        "type": "float32"
    },
    {
        "kind": "struct",
        "name": "fuchsia.ui.gfx/vec4"
    },
    {
        "kind": "library",
        "name": "fuchsia.ui.gfx"
    }
]
