[
    {
        "kind": "protocol/member",
        "name": "fuchsia.developer.tiles/Controller.AddTileFromURL",
        "type": "(string url,bool allow_focus,vector<string>:optional args) -> (uint32 key)"
    },
    {
        "kind": "protocol/member",
        "name": "fuchsia.developer.tiles/Controller.AddTileFromViewProvider",
        "type": "(string url,fuchsia.ui.app/ViewProvider provider) -> (uint32 key)"
    },
    {
        "kind": "protocol/member",
        "name": "fuchsia.developer.tiles/Controller.ListTiles",
        "type": "() -> (vector<uint32> keys,vector<string> urls,vector<fuchsia.ui.gfx/vec3> sizes,vector<bool> focusabilities)"
    },
    {
        "kind": "protocol/member",
        "name": "fuchsia.developer.tiles/Controller.Quit",
        "type": "()"
    },
    {
        "kind": "protocol/member",
        "name": "fuchsia.developer.tiles/Controller.RemoveTile",
        "type": "(uint32 key)"
    },
    {
        "kind": "protocol",
        "name": "fuchsia.developer.tiles/Controller"
    },
    {
        "kind": "library",
        "name": "fuchsia.developer.tiles"
    }
]
