[
    {
        "declaration": "(int32 iface_idx,int32 cmd,vector<uint8>:16384 request) -> (fuchsia.factory.wlan/Iovar_Get_Result result)",
        "kind": "protocol/member",
        "name": "fuchsia.factory.wlan/Iovar.Get"
    },
    {
        "declaration": "(int32 iface_idx,int32 cmd,vector<uint8>:16384 request) -> (fuchsia.factory.wlan/Iovar_Set_Result result)",
        "kind": "protocol/member",
        "name": "fuchsia.factory.wlan/Iovar.Set"
    },
    {
        "kind": "protocol",
        "name": "fuchsia.factory.wlan/Iovar"
    },
    {
        "declaration": "vector<uint8>:16384",
        "kind": "struct/member",
        "name": "fuchsia.factory.wlan/Iovar_Get_Response.result"
    },
    {
        "kind": "struct",
        "name": "fuchsia.factory.wlan/Iovar_Get_Response"
    },
    {
        "declaration": "int32",
        "kind": "union/member",
        "name": "fuchsia.factory.wlan/Iovar_Get_Result.err"
    },
    {
        "declaration": "fuchsia.factory.wlan/Iovar_Get_Response",
        "kind": "union/member",
        "name": "fuchsia.factory.wlan/Iovar_Get_Result.response"
    },
    {
        "kind": "union",
        "name": "fuchsia.factory.wlan/Iovar_Get_Result",
        "strictness": "strict"
    },
    {
        "kind": "struct",
        "name": "fuchsia.factory.wlan/Iovar_Set_Response"
    },
    {
        "declaration": "int32",
        "kind": "union/member",
        "name": "fuchsia.factory.wlan/Iovar_Set_Result.err"
    },
    {
        "declaration": "fuchsia.factory.wlan/Iovar_Set_Response",
        "kind": "union/member",
        "name": "fuchsia.factory.wlan/Iovar_Set_Result.response"
    },
    {
        "kind": "union",
        "name": "fuchsia.factory.wlan/Iovar_Set_Result",
        "strictness": "strict"
    },
    {
        "declaration": "uint64",
        "kind": "const",
        "name": "fuchsia.factory.wlan/MAX_BUFFER_SIZE",
        "value": "16384"
    },
    {
        "kind": "library",
        "name": "fuchsia.factory.wlan"
    }
]
