[
    {
        "kind": "enum/member",
        "name": "fuchsia.hwinfo/Architecture.ARM64",
        "value": "2"
    },
    {
        "kind": "enum/member",
        "name": "fuchsia.hwinfo/Architecture.X64",
        "value": "1"
    },
    {
        "kind": "enum",
        "name": "fuchsia.hwinfo/Architecture",
        "strictness": "flexible",
        "type": "uint32"
    },
    {
        "kind": "protocol/member",
        "name": "fuchsia.hwinfo/Board.GetInfo",
        "type": "() -> (fuchsia.hwinfo/BoardInfo info)"
    },
    {
        "kind": "protocol",
        "name": "fuchsia.hwinfo/Board"
    },
    {
        "kind": "table/member",
        "name": "fuchsia.hwinfo/BoardInfo.cpu_architecture",
        "type": "fuchsia.hwinfo/Architecture"
    },
    {
        "kind": "table/member",
        "name": "fuchsia.hwinfo/BoardInfo.name",
        "type": "string"
    },
    {
        "kind": "table/member",
        "name": "fuchsia.hwinfo/BoardInfo.revision",
        "type": "string"
    },
    {
        "kind": "table",
        "name": "fuchsia.hwinfo/BoardInfo"
    },
    {
        "kind": "protocol/member",
        "name": "fuchsia.hwinfo/Device.GetInfo",
        "type": "() -> (fuchsia.hwinfo/DeviceInfo info)"
    },
    {
        "kind": "protocol",
        "name": "fuchsia.hwinfo/Device"
    },
    {
        "kind": "table/member",
        "name": "fuchsia.hwinfo/DeviceInfo.is_retail_demo",
        "type": "bool"
    },
    {
        "kind": "table/member",
        "name": "fuchsia.hwinfo/DeviceInfo.retail_sku",
        "type": "string:255"
    },
    {
        "kind": "table/member",
        "name": "fuchsia.hwinfo/DeviceInfo.serial_number",
        "type": "string:255"
    },
    {
        "kind": "table",
        "name": "fuchsia.hwinfo/DeviceInfo"
    },
    {
        "kind": "const",
        "name": "fuchsia.hwinfo/MAX_VALUE_SIZE",
        "type": "uint8",
        "value": "255"
    },
    {
        "kind": "protocol/member",
        "name": "fuchsia.hwinfo/Product.GetInfo",
        "type": "() -> (fuchsia.hwinfo/ProductInfo info)"
    },
    {
        "kind": "protocol",
        "name": "fuchsia.hwinfo/Product"
    },
    {
        "kind": "table/member",
        "name": "fuchsia.hwinfo/ProductInfo.audio_amplifier",
        "type": "string:255"
    },
    {
        "kind": "table/member",
        "name": "fuchsia.hwinfo/ProductInfo.build_date",
        "type": "string"
    },
    {
        "kind": "table/member",
        "name": "fuchsia.hwinfo/ProductInfo.build_name",
        "type": "string:255"
    },
    {
        "kind": "table/member",
        "name": "fuchsia.hwinfo/ProductInfo.colorway",
        "type": "string:255"
    },
    {
        "kind": "table/member",
        "name": "fuchsia.hwinfo/ProductInfo.display",
        "type": "string:255"
    },
    {
        "kind": "table/member",
        "name": "fuchsia.hwinfo/ProductInfo.emmc_storage",
        "type": "string:255"
    },
    {
        "kind": "table/member",
        "name": "fuchsia.hwinfo/ProductInfo.language",
        "type": "string"
    },
    {
        "kind": "table/member",
        "name": "fuchsia.hwinfo/ProductInfo.locale_list",
        "type": "vector<fuchsia.intl/LocaleId>"
    },
    {
        "kind": "table/member",
        "name": "fuchsia.hwinfo/ProductInfo.manufacturer",
        "type": "string"
    },
    {
        "kind": "table/member",
        "name": "fuchsia.hwinfo/ProductInfo.memory",
        "type": "string:255"
    },
    {
        "kind": "table/member",
        "name": "fuchsia.hwinfo/ProductInfo.microphone",
        "type": "string:255"
    },
    {
        "kind": "table/member",
        "name": "fuchsia.hwinfo/ProductInfo.model",
        "type": "string"
    },
    {
        "kind": "table/member",
        "name": "fuchsia.hwinfo/ProductInfo.name",
        "type": "string"
    },
    {
        "kind": "table/member",
        "name": "fuchsia.hwinfo/ProductInfo.nand_storage",
        "type": "string:255"
    },
    {
        "kind": "table/member",
        "name": "fuchsia.hwinfo/ProductInfo.regulatory_domain",
        "type": "fuchsia.intl/RegulatoryDomain"
    },
    {
        "kind": "table/member",
        "name": "fuchsia.hwinfo/ProductInfo.sku",
        "type": "string"
    },
    {
        "kind": "table",
        "name": "fuchsia.hwinfo/ProductInfo"
    },
    {
        "kind": "library",
        "name": "fuchsia.hwinfo"
    }
]
