[
    {
        "declaration": "() -> (fuchsia.location.position/EmergencyProvider_GetCurrent_Result result)",
        "kind": "protocol/member",
        "name": "fuchsia.location.position/EmergencyProvider.GetCurrent"
    },
    {
        "kind": "protocol",
        "name": "fuchsia.location.position/EmergencyProvider"
    },
    {
        "declaration": "fuchsia.location.position/Position",
        "kind": "struct/member",
        "name": "fuchsia.location.position/EmergencyProvider_GetCurrent_Response.position"
    },
    {
        "kind": "struct",
        "name": "fuchsia.location.position/EmergencyProvider_GetCurrent_Response"
    },
    {
        "declaration": "fuchsia.location/Error",
        "kind": "union/member",
        "name": "fuchsia.location.position/EmergencyProvider_GetCurrent_Result.err"
    },
    {
        "declaration": "fuchsia.location.position/EmergencyProvider_GetCurrent_Response",
        "kind": "union/member",
        "name": "fuchsia.location.position/EmergencyProvider_GetCurrent_Result.response"
    },
    {
        "kind": "union",
        "name": "fuchsia.location.position/EmergencyProvider_GetCurrent_Result",
        "strictness": "strict"
    },
    {
        "declaration": "fuchsia.location.position/PositionExtras",
        "kind": "struct/member",
        "name": "fuchsia.location.position/Position.extras"
    },
    {
        "declaration": "float64",
        "kind": "struct/member",
        "name": "fuchsia.location.position/Position.latitude"
    },
    {
        "declaration": "float64",
        "kind": "struct/member",
        "name": "fuchsia.location.position/Position.longitude"
    },
    {
        "kind": "struct",
        "name": "fuchsia.location.position/Position"
    },
    {
        "declaration": "float64",
        "kind": "table/member",
        "name": "fuchsia.location.position/PositionExtras.accuracy_meters"
    },
    {
        "declaration": "float64",
        "kind": "table/member",
        "name": "fuchsia.location.position/PositionExtras.altitude_meters"
    },
    {
        "kind": "table",
        "name": "fuchsia.location.position/PositionExtras"
    },
    {
        "kind": "library",
        "name": "fuchsia.location.position"
    }
]
